medicaltorch/__init__.py
medicaltorch/datasets.py
medicaltorch/filters.py
medicaltorch/losses.py
medicaltorch/metrics.py
medicaltorch/models.py
medicaltorch/transforms.py
medicaltorch-0.2.dist-info/LICENSE
medicaltorch-0.2.dist-info/METADATA
medicaltorch-0.2.dist-info/WHEEL
medicaltorch-0.2.dist-info/top_level.txt
medicaltorch-0.2.dist-info/RECORD
