Metadata-Version: 2.1
Name: medicaltorch
Version: 0.2
Summary: An open-source pytorch medical framework.
Home-page: https://github.com/perone/medicaltorch
Author: Christian S. Perone
Author-email: christian.perone@gmail.com
License: UNKNOWN
Platform: UNKNOWN
Classifier: Development Status :: 3 - Alpha
Classifier: Intended Audience :: Developers
Classifier: Programming Language :: Python :: 3
Requires-Dist: nibabel (>=2.2.1)
Requires-Dist: scipy (>=1.0.0)
Requires-Dist: numpy (>=1.14.1)
Requires-Dist: torch (>=0.4.0)
Requires-Dist: torchvision (>=0.2.1)
Requires-Dist: tqdm (>=4.23.0)
